{"created_at": 1780143698.9283495, "ttl_seconds": 5184000, "data": {"suggestion": {"keywords": [], "cities": []}, "count": "196", "infocode": "10000", "pois": [{"parent": "B000A22AC9", "pcode": "110000", "keytag": "创意菜", "type": "餐饮服务;中餐厅;特色/地方风味餐厅", "photos": [{"title": [], "url": "http://store.is.autonavi.com/showpic/4736cb6f2c6cb4756462be0783e53cad"}, {"title": [], "url": "http://store.is.autonavi.com/showpic/f57cd71ad32274322a803e6e0328fec6"}, {"title": [], "url": "http://store.is.autonavi.com/showpic/37d63db3005f2ee0b4ad8c7782761636"}], "building": [], "typecode": "050118", "poiweight": [], "citycode": "010", "adname": "朝阳区", "children": [], "featured_reviews_remake": [], "tel": "010-64380881", "id": "B000A7LAHE", "tag": "大蒜烤牛扒,烤鳗鱼,加州阳光卷,重庆森林,罗兰湖炒饭,大蒜牛肉粒,牛油果鲜虾沙拉,酱烤三文鱼,烤土豆香肠,海螺细面,烤五花肉,铁板烤海鲜拼盘,海鲜大拌菜,烤青花鱼,小牛仔骨,鸡肉,下午茶,牛肉,三文鱼", "entr_location": "116.479317,39.973964", "adcode": "110105", "pname": "北京市", "biz_type": "diner", "cityname": "北京市", "postcode": [], "business_area": "酒仙桥", "childtype": "302", "atag": "大蒜烤牛扒,烤鳗鱼,加州阳光卷,重庆森林,罗兰湖炒饭,大蒜牛肉粒,牛油果鲜虾沙拉,酱烤三文鱼,烤土豆香肠,海螺细面,烤五花肉,铁板烤海鲜拼盘,海鲜大拌菜,烤青花鱼,小牛仔骨,鸡肉,下午茶,牛肉,三文鱼", "name": "罗兰湖餐厅", "shopid": [], "favorite_num": [], "navi_poiid": "J50F001020_217837", "distance": [], "importance": [], "biz_ext": {"cost": "189.00", "opentime2": "周一至周日 11:30-21:30", "rating": "4.8", "open_time": "11:30-21:30", "meal_ordering": "0"}, "recommend": "0", "discount_num": "0", "gridcode": "5916736821", "shopinfo": "0", "alias": [], "event": [], "indoor_map": "0", "email": [], "timestamp": "2026-05-30 15:07:03", "website": [], "address": "芳园西路6号(丽都花园内)", "space_num": [], "match": "0", "indoor_data": {"cmsid": [], "truefloor": [], "cpid": [], "floor": []}, "exit_location": [], "location": "116.479365,39.973868", "groupbuy_num": "0", "featured_reviews": []}, {"parent": [], "pcode": "110000", "keytag": "融合菜", "type": "购物服务;专卖店;书店", "photos": [{"title": [], "url": "http://store.is.autonavi.com/showpic/099b1fbd4a0f7a7e6fec64d758c741c4"}, {"title": [], "url": "https://aos-comment.amap.com/B0KGB539Y8/comment/f8d441944c945037bd1d40f5a13285ae_2048_2048_80.jpg"}, {"title": [], "url": "http://store.is.autonavi.com/showpic/7ef7c610866a924c930e4759d2ba32d6"}], "building": [], "typecode": "061205", "poiweight": [], "citycode": "010", "adname": "西城区", "children": [], "featured_reviews_remake": [], "tel": "13901111351", "id": "B0KGB539Y8", "tag": "白塔素烧鹅,白塔精选冷菜四拼,荔枝酥皮大明虾,白塔宫保海陆空,单人餐", "entr_location": "116.363841,39.925490", "adcode": "110102", "pname": "北京市", "biz_type": [], "cityname": "北京市", "postcode": [], "business_area": "官园", "childtype": [], "atag": "白塔素烧鹅,白塔精选冷菜四拼,荔枝酥皮大明虾,白塔宫保海陆空,单人餐", "name": "白塔书院·精致中菜(金融街白塔寺店)", "shopid": [], "favorite_num": [], "navi_poiid": [], "distance": [], "importance": [], "biz_ext": {"cost": "114.00", "opentime2": "周一至周日 10:00-22:00", "rating": "4.7", "open_time": "10:00-22:00"}, "recommend": "0", "discount_num": "0", "gridcode": "5916721900", "shopinfo": "0", "alias": [], "event": [], "indoor_map": "0", "email": [], "timestamp": "2026-05-30 00:15:18", "website": [], "address": "北京城区白塔寺东夹道21号", "space_num": [], "match": "0", "indoor_data": {"cmsid": [], "truefloor": [], "cpid": [], "floor": []}, "exit_location": [], "location": "116.363837,39.925570", "groupbuy_num": "0", "featured_reviews": []}, {"parent": [], "pcode": "110000", "keytag": "西餐", "type": "餐饮服务;餐饮相关场所;餐饮相关", "photos": [{"title": [], "url": "https://store.is.autonavi.com/showpic/427f684b09fac4bc0000002434660999?type=pic"}, {"title": [], "url": "https://aos-comment.amap.com/B0LG7MUZ1B/comment/content_media_external_images_media_100004415_1744730475524_10258662.jpg"}, {"title": [], "url": "https://aos-comment.amap.com/B0LG7MUZ1B/comment/content_media_external_file_100004548_1745044392987_53292539.jpg"}], "building": [], "typecode": "050000", "poiweight": [], "citycode": "010", "adname": "顺义区", "children": [], "featured_reviews_remake": [], "tel": "13001009201", "id": "B0LG7MUZ1B", "tag": "手工三文鱼酱配自制碳烤软饼,慢炖手撕猪肉意面,果木碳烤春鸡,和牛塔塔,经典拿铁咖啡,下午茶", "entr_location": "116.509400,40.081398", "adcode": "110113", "pname": "北京市", "biz_type": "diner", "cityname": "北京市", "postcode": [], "business_area": "后沙峪", "childtype": [], "atag": "手工三文鱼酱配自制碳烤软饼,慢炖手撕猪肉意面,果木碳烤春鸡,和牛塔塔,经典拿铁咖啡,下午茶", "name": "GRANVISTA 观境", "shopid": [], "favorite_num": [], "navi_poiid": [], "distance": [], "importance": [], "biz_ext": {"cost": "134.00", "opentime2": "周一至周日 10:00-22:00", "rating": "4.6", "open_time": "10:00-22:00", "meal_ordering": "0"}, "recommend": "0", "discount_num": "0", "gridcode": "6016049022", "shopinfo": "0", "alias": [], "event": [], "indoor_map": "0", "email": [], "timestamp": "2026-05-30 11:35:07", "website": [], "address": "龙湾别墅东南门9-2", "space_num": [], "match": "0", "indoor_data": {"cmsid": [], "truefloor": [], "cpid": [], "floor": []}, "exit_location": [], "location": "116.509247,40.081430", "groupbuy_num": "0", "featured_reviews": []}, {"parent": [], "pcode": "110000", "keytag": "中餐", "type": "餐饮服务;中餐厅;中餐厅", "photos": [{"title": [], "url": "http://store.is.autonavi.com/showpic/368e5c3803d021d3f273a45c67bae53a"}, {"title": [], "url": "https://aos-comment.amap.com/B0FFKEBA68/comment/14737a05b3fd2664d18659531a047a27_2048_2048_80.jpg"}, {"title": [], "url": "https://aos-comment.amap.com/B0FFKEBA68/comment/2F5DE870_3542_47B5_BBDD_15EC08FDA59A_L0_001_IMG_5040_1656899339900_38d5a187.HEIC"}], "building": [], "typecode": "050100", "poiweight": [], "citycode": "010", "adname": "通州区", "children": [], "featured_reviews_remake": [], "tel": "010-81555518", "id": "B0FFKEBA68", "tag": "红烧西施鱼,遇上佛跳墙,台州家烧大黄鱼,葱烧海参,烤鸭,双人餐,老北京驴打滚", "entr_location": "116.696724,39.907958", "adcode": "110112", "pname": "北京市", "biz_type": "diner", "cityname": "北京市", "postcode": [], "business_area": "乔庄", "childtype": [], "atag": "红烧西施鱼,遇上佛跳墙,台州家烧大黄鱼,葱烧海参,烤鸭,双人餐,老北京驴打滚", "name": "遇上·烤鸭·创意中国菜(运河店)", "shopid": [], "favorite_num": [], "navi_poiid": [], "distance": [], "importance": [], "biz_ext": {"cost": "138.00", "opentime2": "周一至周日 10:30-21:30", "rating": "4.6", "open_time": "10:30-21:30", "meal_ordering": "0"}, "recommend": "0", "discount_num": "0", "gridcode": "5916658522", "shopinfo": "0", "alias": [], "event": [], "indoor_map": "0", "email": [], "timestamp": "2026-05-26 00:03:01", "website": [], "address": "北京城区水仙西路85号85-01", "space_num": [], "match": "0", "indoor_data": {"cmsid": [], "truefloor": [], "cpid": [], "floor": []}, "exit_location": [], "location": "116.696802,39.907792", "groupbuy_num": "0", "featured_reviews": []}, {"parent": "B0FFF5MUMY", "pcode": "110000", "keytag": "清吧", "type": "餐饮服务;咖啡厅;咖啡厅", "photos": [{"title": [], "url": "https://store.is.autonavi.com/showpic/6d19050cf89f3b9f0000000708738509?type=pic"}, {"title": [], "url": "https://store.is.autonavi.com/showpic/2e642f6725e38a9e0000000967942559?type=pic"}, {"title": [], "url": "https://aos-comment.amap.com/B0L246MYSN/comment/BB982173_223E_493F_8E90_59F005E49CAA_L0_001_1500_200_1761613836073_58676996.jpg"}], "building": [], "typecode": "050500", "poiweight": [], "citycode": "010", "adname": "东城区", "children": [], "featured_reviews_remake": [], "tel": "13011030253", "id": "B0L246MYSN", "tag": [], "entr_location": "116.429810,39.924872", "adcode": "110101", "pname": "北京市", "biz_type": "diner", "cityname": "北京市", "postcode": [], "business_area": "东四", "childtype": "302", "atag": [], "name": "發福fafu Bistro·Cafe", "shopid": [], "favorite_num": [], "navi_poiid": [], "distance": [], "importance": [], "biz_ext": {"cost": "120.00", "opentime2": "周一至周日 11:00-24:00", "rating": "4.6", "open_time": "11:00-24:00", "meal_ordering": "0"}, "recommend": "0", "discount_num": "0", "gridcode": "5916730421", "shopinfo": "0", "alias": [], "event": [], "indoor_map": "0", "email": [], "timestamp": "2026-05-25 13:34:24", "website": [], "address": "北京城区朝内大街81号(东北角)", "space_num": [], "match": "0", "indoor_data": {"cmsid": [], "truefloor": [], "cpid": [], "floor": []}, "exit_location": [], "location": "116.429636,39.924990", "groupbuy_num": "0", "featured_reviews": []}, {"parent": "B0FFF4E2YZ", "pcode": "110000", "keytag": "夜宵", "type": "餐饮服务;中餐厅;中餐厅", "photos": [{"title": [], "url": "https://store.is.autonavi.com/showpic/c20ad34a337a9a7d0000002434380829?type=pic"}, {"title": [], "url": "http://store.is.autonavi.com/showpic/80487bba9c578a6a30384b22a08bf61a"}, {"title": [], "url": "https://aos-comment.amap.com/B0HDK5DZT8/comment/15dcaa6434d260544274bf78ef329ca6_2048_2048_80.jpg"}], "building": [], "typecode": "050100", "poiweight": [], "citycode": "010", "adname": "朝阳区", "children": [], "featured_reviews_remake": [], "tel": "010-62078858;010-82078858", "id": "B0HDK5DZT8", "tag": "虾仁,胡辣汤,融合菜,羊排,鱼鲜,西湖醋鱼,龙井虾仁", "entr_location": "116.393034,39.978476", "adcode": "110105", "pname": "北京市", "biz_type": "diner", "cityname": "北京市", "postcode": [], "business_area": "北辰", "childtype": "302", "atag": "虾仁,胡辣汤,融合菜,羊排,鱼鲜,西湖醋鱼,龙井虾仁", "name": "金狮麟·宋宴", "shopid": [], "favorite_num": [], "navi_poiid": [], "distance": [], "importance": [], "biz_ext": {"cost": "302.00", "opentime2": "周一至周日 17:00-24:00", "rating": "4.7", "open_time": "17:00-24:00", "meal_ordering": "0"}, "recommend": "0", "discount_num": "0", "gridcode": "5916737111", "shopinfo": "1", "alias": [], "event": [], "indoor_map": "0", "email": [], "timestamp": "2026-05-30 19:33:20", "website": [], "address": "北土城地铁A出口西侧(北土城地铁站A西北口步行150米)", "space_num": [], "match": "0", "indoor_data": {"cmsid": [], "truefloor": [], "cpid": [], "floor": []}, "exit_location": [], "location": "116.392915,39.978448", "groupbuy_num": "0", "featured_reviews": []}, {"parent": "B000A88EG4", "pcode": "110000", "keytag": "北京菜", "type": "餐饮服务;餐饮相关场所;餐饮相关", "photos": [{"title": [], "url": "http://store.is.autonavi.com/query_pic?id=st0d825bf4-a484-4a0d-b153-b2f1a9d2c7e1&user=search&operate=original"}, {"title": [], "url": "https://store.is.autonavi.com/showpic/ec6363b8d412090e06cc056f49ee0e1a"}, {"title": [], "url": "https://aos-comment.amap.com/B0H23BQ011/comment/content_media_external_file_173417_ss__1771211729106_57644773.jpg"}], "building": [], "typecode": "050000", "poiweight": [], "citycode": "010", "adname": "朝阳区", "children": [], "featured_reviews_remake": [], "tel": "010-64100677;010-64100877", "id": "B0H23BQ011", "tag": "牛肉,双人餐,烤鸭", "entr_location": "116.455408,39.934397", "adcode": "110105", "pname": "北京市", "biz_type": "diner", "cityname": "北京市", "postcode": [], "business_area": "三里屯", "childtype": "202", "atag": "牛肉,双人餐,烤鸭", "name": "提督臻选·TIDU RESERVE(三里屯太古里南区店)", "shopid": [], "favorite_num": [], "navi_poiid": [], "distance": [], "importance": [], "biz_ext": {"cost": "188.00", "opentime2": "周一至周五 11:00-14:30,16:30-21:30；周六至周日 11:00-22:00 2026-05-01至2026-05-05 11:00-22:30", "rating": "4.6", "open_time": "11:00-22:00 11:00-22:30", "meal_ordering": "0"}, "recommend": "0", "discount_num": "0", "gridcode": "5916732601", "shopinfo": "0", "alias": [], "event": [], "indoor_map": "0", "email": [], "timestamp": "2026-05-30 15:29:40", "website": [], "address": "三里屯路19号三里屯太古里南区L4层", "space_num": [], "match": "0", "indoor_data": {"cmsid": [], "truefloor": [], "cpid": [], "floor": []}, "exit_location": [], "location": "116.455066,39.934392", "groupbuy_num": "0", "featured_reviews": []}, {"parent": [], "pcode": "110000", "keytag": "创意菜", "type": "餐饮服务;中餐厅;中餐厅|餐饮服务;休闲餐饮场所;休闲餐饮场所", "photos": [{"title": [], "url": "https://aos-comment.amap.com/B0H14UTUNV/comment/44085A04_B226_4A21_941E_408EA2CB62D9_L0_001_1500_200_1763511829785_64920081.jpg"}, {"title": [], "url": "https://aos-comment.amap.com/B0H14UTUNV/comment/47c2295dd1560565aa63aaf8d13f19b2_2048_2048_80.jpg"}, {"title": [], "url": "https://aos-comment.amap.com/B0H14UTUNV/comment/925573006c85ef1d865e05737c6ee072_2048_2048_80.jpg"}], "building": [], "typecode": "050100|050400", "poiweight": [], "citycode": "010", "adname": "朝阳区", "children": [], "featured_reviews_remake": [], "tel": "13693071462", "id": "B0H14UTUNV", "tag": "下午茶,牛肉,双人餐,鸡肉", "entr_location": "116.453997,39.938368", "adcode": "110105", "pname": "北京市", "biz_type": "diner", "cityname": "北京市", "postcode": [], "business_area": "三里屯", "childtype": [], "atag": "下午茶,牛肉,双人餐,鸡肉", "name": "元古雲境", "shopid": [], "favorite_num": [], "navi_poiid": [], "distance": [], "importance": [], "biz_ext": {"cost": "206.00", "opentime2": "11:00-01:00,2026年2月16日 00:00-14:00,2月17日至3月3日 11:00-22:00", "rating": "4.7", "open_time": [], "meal_ordering": "0"}, "recommend": "0", "discount_num": "0", "gridcode": "5916732610", "shopinfo": "1", "alias": [], "event": [], "indoor_map": "1", "email": [], "timestamp": "2026-05-30 19:09:18", "website": [], "address": "三里屯路11号太古里北区N4三层(Kenzo旁扶梯上)", "space_num": [], "match": "0", "indoor_data": {"cmsid": "47200210302046", "truefloor": "L3", "cpid": "B000A85N3Y", "floor": "3"}, "exit_location": [], "location": "116.453900,39.938142", "groupbuy_num": "0", "featured_reviews": []}, {"parent": "B0FFFZDN3B", "pcode": "110000", "keytag": "创意菜", "type": "餐饮服务;中餐厅;中餐厅", "photos": [{"title": [], "url": "https://aos-comment.amap.com/B0JAZAVC68/comment/content_media_external_file_100000817_1746639091345_10909907.jpg"}, {"title": [], "url": "https://aos-comment.amap.com/B0JAZAVC68/comment/content_media_external_images_media_100000093_1759158650338_86499261.jpg"}, {"title": [], "url": "https://aos-comment.amap.com/B0JAZAVC68/comment/content_media_external_file_431262_1769877237550_68499357.jpg"}], "building": [], "typecode": "050100", "poiweight": [], "citycode": "010", "adname": "昌平区", "children": [], "featured_reviews_remake": [], "tel": "18613310557", "id": "B0JAZAVC68", "tag": "真·红烧明太鱼,榴莲耶律虾,茶啊冲锅包肉,牛舌,素菜,肥牛,土豆泥,烤串,麻辣烫,锅包肉,双人餐,肥肠,豆腐,锅包肉", "entr_location": "116.343599,40.0877", "adcode": "110114", "pname": "北京市", "biz_type": "diner", "cityname": "北京市", "postcode": [], "business_area": "回龙观", "childtype": "202", "atag": "真·红烧明太鱼,榴莲耶律虾,茶啊冲锅包肉,牛舌,素菜,肥牛,土豆泥,烤串,麻辣烫,锅包肉,双人餐,肥肠,豆腐,锅包肉", "name": "随园食记(禧乐汇店)", "shopid": [], "favorite_num": [], "navi_poiid": [], "distance": [], "importance": [], "biz_ext": {"cost": "87.00", "opentime2": "周一至周五 11:00-14:00,17:00-22:00；周六至周日 11:00-22:00 2026-02-13至2026-02-23 周一至周日 11:00-14:00,17:00-22:00", "rating": "4.7", "open_time": "11:00-22:00 11:00-14:00 17:00-22:00", "meal_ordering": "0"}, "recommend": "0", "discount_num": "0", "gridcode": "6016120711", "shopinfo": "0", "alias": [], "event": [], "indoor_map": "0", "email": [], "timestamp": "2026-05-29 22:48:18", "website": [], "address": "文华路89号院1栋(禧乐汇南行100米)", "space_num": [], "match": "0", "indoor_data": {"cmsid": [], "truefloor": [], "cpid": [], "floor": []}, "exit_location": [], "location": "116.343319,40.087659", "groupbuy_num": "0", "featured_reviews": []}, {"parent": "B0H6RU92AP", "pcode": "110000", "keytag": "创意菜", "type": "餐饮服务;中餐厅;西北菜", "photos": [{"title": [], "url": "http://store.is.autonavi.com/showpic/82d94819da09b6026d76d7bc902de7e3"}, {"title": [], "url": "https://aos-comment.amap.com/B0GR17XFL0/comment/content_media_external_images_media_1000114387_ss__1727874139946_03949068.jpg"}, {"title": [], "url": "https://aos-comment.amap.com/B0GR17XFL0/comment/content_media_external_images_media_7999_ss__1764948783398_09224382.jpg"}], "building": [], "typecode": "050115", "poiweight": [], "citycode": "010", "adname": "海淀区", "children": [], "featured_reviews_remake": [], "tel": "13126766167", "id": "B0GR17XFL0", "tag": "单人餐,双人餐,私房菜", "entr_location": "116.283251,39.912763", "adcode": "110108", "pname": "北京市", "biz_type": "diner", "cityname": "北京市", "postcode": [], "business_area": "五棵松", "childtype": "202", "atag": "单人餐,双人餐,私房菜", "name": "杏花堂晋商私房菜(华熙五棵松店)", "shopid": [], "favorite_num": [], "navi_poiid": [], "distance": [], "importance": [], "biz_ext": {"cost": "157.00", "opentime2": "周一至周日 10:30-14:30,17:00-21:30", "rating": "4.6", "open_time": "10:30-14:30 17:00-21:30", "meal_ordering": "0"}, "recommend": "0", "discount_num": "0", "gridcode": "5916629211", "shopinfo": "0", "alias": [], "event": [], "indoor_map": "1", "email": [], "timestamp": "2026-05-30 09:48:12", "website": [], "address": "复兴路69号院五棵松华熙LIVE中心B座202", "space_num": [], "match": "0", "indoor_data": {"cmsid": "HN0000800210101105", "truefloor": "F1", "cpid": "B0H6RU92AP", "floor": "1"}, "exit_location": [], "location": "116.282781,39.912426", "groupbuy_num": "0", "featured_reviews": []}, {"parent": [], "pcode": "110000", "keytag": "中餐", "type": "餐饮服务;中餐厅;中餐厅", "photos": [{"title": [], "url": "https://aos-comment.amap.com/B0FFFHMSCX/comment/file_media_Photo_9325_IMG_1770206300_9060_IMG_20260204_195640_jpg_ss__1770377610620_70461382.jpg"}, {"title": [], "url": "https://store.is.autonavi.com/showpic/328ed180ab21616b12258b93200b0f83"}, {"title": [], "url": "https://store.is.autonavi.com/showpic/54c79b4b23947f640000001987748422?type=pic"}], "building": [], "typecode": "050100", "poiweight": [], "citycode": "010", "adname": "通州区", "children": [], "featured_reviews_remake": [], "tel": "010-80856080;13121684686", "id": "B0FFFHMSCX", "tag": "单人餐,豆腐,红糖糍粑,水煮鱼,水煮鱼,富贵毛血旺,炸酱面", "entr_location": "116.716239,39.946164", "adcode": "110112", "pname": "北京市", "biz_type": "diner", "cityname": "北京市", "postcode": [], "business_area": [], "childtype": [], "atag": "单人餐,豆腐,红糖糍粑,水煮鱼,水煮鱼,富贵毛血旺,炸酱面", "name": "苹果树下艺术餐厅", "shopid": [], "favorite_num": [], "navi_poiid": [], "distance": [], "importance": [], "biz_ext": {"cost": "88.00", "opentime2": "周一至周日 11:00-22:00", "rating": "4.7", "open_time": "11:00-22:00", "meal_ordering": "0"}, "recommend": "0", "discount_num": "0", "gridcode": "5916753710", "shopinfo": "0", "alias": [], "event": [], "indoor_map": "0", "email": [], "timestamp": "2026-05-30 11:56:53", "website": [], "address": "宋庄小堡西街146号", "space_num": [], "match": "0", "indoor_data": {"cmsid": [], "truefloor": [], "cpid": [], "floor": []}, "exit_location": [], "location": "116.716005,39.946200", "groupbuy_num": "0", "featured_reviews": []}, {"parent": "B000A80HJL", "pcode": "110000", "keytag": "融合菜", "type": "餐饮服务;中餐厅;海鲜酒楼", "photos": [{"title": [], "url": "https://aos-comment.amap.com/B000A85LO4/comment/4CB7B337_2BAA_4F97_A0AD_580586B72B1A_L0_001_1500_200_1768545395213_45534602.jpg"}, {"title": [], "url": "https://aos-comment.amap.com/comment/content_service_3f34327ae3c5483a91151a81e8d527f7_1768530938201_26720333.jpg"}, {"title": [], "url": "https://aos-comment.amap.com/B000A85LO4/comment/3FA320F6_AACB_4971_98D0_F23BDABE5A57_L0_001_1276_170_1768372920555_66322651.jpg"}], "building": [], "typecode": "050119", "poiweight": [], "citycode": "010", "adname": "东城区", "children": [], "featured_reviews_remake": [], "tel": "15010065913", "id": "B000A85LO4", "tag": "居桢虾饺皇,金酱蒸凤爪,馋嘴蛙,流沙包,大汉酱牛肉,金牌蛋挞,飘香榴莲酥,叉烧酥,酸菜鱼,宫保鸡丁,居桢益身汤,富士雪山包,白灼唐生菜,重庆毛血旺,鲈鱼,双人餐", "entr_location": "116.431744,39.938418", "adcode": "110101", "pname": "北京市", "biz_type": "diner", "cityname": "北京市", "postcode": [], "business_area": "东四", "childtype": "202", "atag": "居桢虾饺皇,金酱蒸凤爪,馋嘴蛙,流沙包,大汉酱牛肉,金牌蛋挞,飘香榴莲酥,叉烧酥,酸菜鱼,宫保鸡丁,居桢益身汤,富士雪山包,白灼唐生菜,重庆毛血旺,鲈鱼,双人餐", "name": "居桢荟·京湘粤·融合菜(东直门店)", "shopid": [], "favorite_num": [], "navi_poiid": "J50F001020_250669", "distance": [], "importance": [], "biz_ext": {"cost": "93.00", "opentime2": "周一至周日 10:00-14:30,17:00-23:00", "rating": "4.7", "open_time": "10:00-14:30 17:00-23:00", "meal_ordering": "0"}, "recommend": "0", "discount_num": "0", "gridcode": "5916732411", "shopinfo": "0", "alias": [], "event": [], "indoor_map": "0", "email": [], "timestamp": "2026-05-30 02:01:37", "website": [], "address": "东直门南大街甲3号居然大厦2-3层", "space_num": [], "match": "0", "indoor_data": {"cmsid": [], "truefloor": [], "cpid": [], "floor": []}, "exit_location": [], "location": "116.432078,39.938450", "groupbuy_num": "0", "featured_reviews": []}, {"parent": [], "pcode": "110000", "keytag": "创意菜", "type": "体育休闲服务;娱乐场所;酒吧", "photos": [{"title": [], "url": "https://aos-comment.amap.com/B0LDRSBM3E/comment/content_media_external_file_100000266_1750776805125_25247401.jpg"}, {"title": [], "url": "https://aos-comment.amap.com/B0LDRSBM3E/comment/content_media_external_file_100000086_1754020833311_58345747.jpg"}, {"title": [], "url": "https://aos-comment.amap.com/B0LDRSBM3E/comment/ED3D6F11_FCCB_450F_B77F_E8BC198DA55C_L0_001_IMG_571_1762060798198_98529389.jpg"}], "building": [], "typecode": "080304", "poiweight": [], "citycode": "010", "adname": "朝阳区", "children": [], "featured_reviews_remake": [], "tel": "13240326660;13401042194", "id": "B0LDRSBM3E", "tag": [], "entr_location": "116.455855,39.948458", "adcode": "110105", "pname": "北京市", "biz_type": [], "cityname": "北京市", "postcode": [], "business_area": "燕莎", "childtype": [], "atag": [], "name": "利利酒馆 LILY LUSH", "shopid": [], "favorite_num": [], "navi_poiid": [], "distance": [], "importance": [], "biz_ext": {"cost": "222.00", "opentime2": "周一至周日 18:00-02:00", "rating": "4.7", "open_time": "18:00-02:00"}, "recommend": "0", "discount_num": "0", "gridcode": "5916733621", "shopinfo": "0", "alias": [], "event": [], "indoor_map": "0", "email": [], "timestamp": "2026-05-29 15:28:57", "website": [], "address": "新源南路与新源街交叉口东北40米", "space_num": [], "match": "0", "indoor_data": {"cmsid": [], "truefloor": [], "cpid": [], "floor": []}, "exit_location": [], "location": "116.455825,39.948575", "groupbuy_num": "0", "featured_reviews": []}, {"parent": [], "pcode": "110000", "keytag": "川菜", "type": "餐饮服务;中餐厅;中餐厅", "photos": [{"title": [], "url": "https://aos-comment.amap.com/B0H1TCJYO9/comment/content_media_external_file_133703_ss__1754459730214_58494309.jpg"}, {"title": [], "url": "https://aos-comment.amap.com/B0H1TCJYO9/comment/AFFD8F96_DF22_41F4_9051_6F1E7162DFE9_L0_001_2016_151_1763481464785_13598584.jpg"}, {"title": [], "url": "https://aos-comment.amap.com/B0H1TCJYO9/comment/C329E106_64A2_4883_BBC1_4BEE0EA63E3C_L0_001_1160_128_1772692362625_90856878.jpg"}], "building": [], "typecode": "050100", "poiweight": [], "citycode": "010", "adname": "西城区", "children": [], "featured_reviews_remake": [], "tel": "13522765640", "id": "B0H1TCJYO9", "tag": "金牌水煮鱼,歌乐山辣子鸡,招牌青花椒冲浪毛肚,火爆腰花,大师经典烤鸭,星厨鱼子酱烤鸭,毛肚,牛肉,鸡肉,单人餐,水煮鱼,烤鸭,牛排,海鲜毛血旺,相濡以沫夫妻肺片,蜀海游龙水煮鱼", "entr_location": [], "adcode": "110102", "pname": "北京市", "biz_type": "diner", "cityname": "北京市", "postcode": [], "business_area": "金融街", "childtype": [], "atag": "金牌水煮鱼,歌乐山辣子鸡,招牌青花椒冲浪毛肚,火爆腰花,大师经典烤鸭,星厨鱼子酱烤鸭,毛肚,牛肉,鸡肉,单人餐,水煮鱼,烤鸭,牛排,海鲜毛血旺,相濡以沫夫妻肺片,蜀海游龙水煮鱼", "name": "怡己巷子•精致中菜(金融街店)", "shopid": [], "favorite_num": [], "navi_poiid": [], "distance": [], "importance": [], "biz_ext": {"cost": "158.00", "opentime2": "周一至周日 11:00-14:00,16:30-22:00", "rating": "4.6", "open_time": "11:00-14:00 16:30-22:00", "meal_ordering": "0"}, "recommend": "0", "discount_num": "0", "gridcode": "5916720900", "shopinfo": "0", "alias": [], "event": [], "indoor_map": "0", "email": [], "timestamp": "2026-05-26 03:26:08", "website": [], "address": "金城坊街9号大楼", "space_num": [], "match": "0", "indoor_data": {"cmsid": [], "truefloor": [], "cpid": [], "floor": []}, "exit_location": [], "location": "116.362779,39.916834", "groupbuy_num": "0", "featured_reviews": []}, {"parent": "B000A7C1AE", "pcode": "110000", "keytag": "创意菜", "type": "餐饮服务;外国餐厅;泰国/越南菜品餐厅", "photos": [{"title": [], "url": "http://store.is.autonavi.com/showpic/2b2eee97be1e683bf5eec603269436b8"}, {"title": [], "url": "http://store.is.autonavi.com/showpic/7c5c3cf23664ae75b874b7ffb5773923"}, {"title": [], "url": "https://store.is.autonavi.com/showpic/6433dc41c82faf4af5e1e54e3c9b24d9"}], "building": [], "typecode": "050206", "poiweight": [], "citycode": "010", "adname": "海淀区", "children": [], "featured_reviews_remake": [], "tel": "010-88213345", "id": "B000A7CKPH", "tag": "香叶炒肉末,冬阴功汤,招牌黄咖喱炒蟹,蕉叶香茅烤青鱼,泰式炒什菜,炭烤猪颈肉,菠萝饭,黄咖喱炒虾,柚子沙拉,椰汁黑糯米,料理,鸡肉,排骨", "entr_location": "116.264944,39.909036", "adcode": "110108", "pname": "北京市", "biz_type": "diner", "cityname": "北京市", "postcode": "100039", "business_area": "五棵松", "childtype": "202", "atag": "香叶炒肉末,冬阴功汤,招牌黄咖喱炒蟹,蕉叶香茅烤青鱼,泰式炒什菜,炭烤猪颈肉,菠萝饭,黄咖喱炒虾,柚子沙拉,椰汁黑糯米,料理,鸡肉,排骨", "name": "苏泰·辣椒餐厅(北京长峰假日酒店店)", "shopid": [], "favorite_num": [], "navi_poiid": "J50F002019_280918", "distance": [], "importance": [], "biz_ext": {"cost": "159.00", "opentime2": "周一至周日 11:30-14:30,17:00-22:00", "rating": "4.6", "open_time": "11:30-14:30 17:00-22:00", "meal_ordering": "0"}, "recommend": "0", "discount_num": "0", "gridcode": "5916629100", "shopinfo": "0", "alias": [], "event": [], "indoor_map": "0", "email": [], "timestamp": "2026-05-26 01:05:03", "website": [], "address": "永定路66号北京长峰假日酒店1层", "space_num": [], "match": "0", "indoor_data": {"cmsid": [], "truefloor": [], "cpid": [], "floor": []}, "exit_location": [], "location": "116.265118,39.909017", "groupbuy_num": "0", "featured_reviews": []}, {"parent": "B0FFFAH7I9", "pcode": "110000", "keytag": "创意菜", "type": "商务住宅;商务住宅相关;商务住宅相关", "photos": [{"title": [], "url": "https://store.is.autonavi.com/showpic/df28ab9d19e0e0390000002255210797?type=pic"}, {"title": [], "url": "https://aos-comment.amap.com/B0H6OHSJJ8/comment/A43F2395_77CF_4CC5_BB65_B66147ED04A4_L0_001_1707_1280_1728866083898_28049552.jpg"}, {"title": [], "url": "https://aos-comment.amap.com/B0H6OHSJJ8/comment/1554208e0427b0d9444dd86aed7a195f_2048_2048_80.jpg"}], "building": [], "typecode": "120000", "poiweight": [], "citycode": "010", "adname": "东城区", "children": [], "featured_reviews_remake": [], "tel": "010-67020888", "id": "B0H6OHSJJ8", "tag": "北京红酒酥不腻烤鸭,“雪茄”春卷,官燕杨枝甘露,荷唐翅羹,干邑樱桃鹅肝,蜜汁叉烧黑豚,龙虾,杨枝甘露,烤鸭,升级版毛血旺,传统春饼,川南水煮牛肉,雪茄春卷", "entr_location": "116.402288,39.933501", "adcode": "110101", "pname": "北京市", "biz_type": [], "cityname": "北京市", "postcode": [], "business_area": "沙滩", "childtype": "302", "atag": "北京红酒酥不腻烤鸭,“雪茄”春卷,官燕杨枝甘露,荷唐翅羹,干邑樱桃鹅肝,蜜汁叉烧黑豚,龙虾,杨枝甘露,烤鸭,升级版毛血旺,传统春饼,川南水煮牛肉,雪茄春卷", "name": "荷唐·殿Home Town Palace", "shopid": [], "favorite_num": [], "navi_poiid": [], "distance": [], "importance": [], "biz_ext": {"cost": "234.00", "opentime2": "周一至周日 11:00-14:00,17:00-21:00", "rating": "4.6", "open_time": "11:00-14:00 17:00-21:00"}, "recommend": "0", "discount_num": "0", "gridcode": "5916732200", "shopinfo": "0", "alias": [], "event": [], "indoor_map": "0", "email": [], "timestamp": "2026-05-26 06:07:23", "website": [], "address": "地安门东大街89-1号(南锣鼓巷地铁站E西北口步行70米)", "space_num": [], "match": "0", "indoor_data": {"cmsid": [], "truefloor": [], "cpid": [], "floor": []}, "exit_location": [], "location": "116.402310,39.933615", "groupbuy_num": "0", "featured_reviews": []}, {"parent": "B0GDSHS2FJ", "pcode": "110000", "keytag": "创意菜", "type": "餐饮服务;中餐厅;中餐厅", "photos": [{"title": [], "url": "http://store.is.autonavi.com/showpic/37fc80aea3c9b86283160fe6c5137348"}, {"title": [], "url": "https://aos-comment.amap.com/B0IU9RXIHM/comment/content_media_external_images_media_10405_1729172296515_66104813.jpg"}, {"title": [], "url": "https://aos-comment.amap.com/B0IU9RXIHM/comment/content_media_external_images_media_247610_ss__1762615872606_56733418.jpg"}], "building": [], "typecode": "050100", "poiweight": [], "citycode": "010", "adname": "石景山区", "children": [], "featured_reviews_remake": [], "tel": "13661114734", "id": "B0IU9RXIHM", "tag": "双人餐,私房菜", "entr_location": [], "adcode": "110107", "pname": "北京市", "biz_type": "diner", "cityname": "北京市", "postcode": [], "business_area": [], "childtype": "202", "atag": "双人餐,私房菜", "name": "杏花堂晋商私房菜(金安环宇荟店)", "shopid": [], "favorite_num": [], "navi_poiid": [], "distance": [], "importance": [], "biz_ext": {"cost": "126.00", "opentime2": "周一至周日 10:30-14:30,17:30-21:30 2026-05-01至2026-05-05 周一至周日 10:30-14:30,17:30-21:30", "rating": "4.6", "open_time": "10:30-14:30 17:30-21:30 10:30-14:30 17:30-21:30", "meal_ordering": "0"}, "recommend": "0", "discount_num": "0", "gridcode": "5916710222", "shopinfo": "0", "alias": [], "event": [], "indoor_map": "0", "email": [], "timestamp": "2026-05-30 15:27:51", "website": [], "address": "和平西路55号院3号楼二层", "space_num": [], "match": "0", "indoor_data": {"cmsid": [], "truefloor": [], "cpid": [], "floor": []}, "exit_location": [], "location": "116.161923,39.923179", "groupbuy_num": "0", "featured_reviews": []}, {"parent": [], "pcode": "110000", "keytag": "创意菜", "type": "体育休闲服务;体育休闲服务场所;体育休闲服务场所|餐饮服务;餐饮相关场所;餐饮相关", "photos": [{"title": [], "url": "https://store.is.autonavi.com/showpic/5c5ec2c78b58fcc7717d8d39003128f2"}, {"title": [], "url": "https://store.is.autonavi.com/showpic/b3fb2e8ee61d47ed0000000962250466?type=pic"}, {"title": [], "url": "https://aos-comment.amap.com/B0J0D6HENC/comment/A011A8E7_E251_438A_A442_3D8620D1AD17_L0_001_1500_200_1744951693729_86472235.jpg"}], "building": [], "typecode": "080000|050000", "poiweight": [], "citycode": "010", "adname": "朝阳区", "children": [], "featured_reviews_remake": [], "tel": "17310969680", "id": "B0J0D6HENC", "tag": [], "entr_location": "116.466198,39.961337", "adcode": "110105", "pname": "北京市", "biz_type": [], "cityname": "北京市", "postcode": [], "business_area": "亮马桥", "childtype": [], "atag": [], "name": "樂福BISTRO", "shopid": [], "favorite_num": [], "navi_poiid": [], "distance": [], "importance": [], "biz_ext": {"cost": "170.00", "opentime2": "周一至周日 17:30-01:00", "rating": "4.7", "open_time": "17:30-01:00", "meal_ordering": "0"}, "recommend": "0", "discount_num": "0", "gridcode": "5916735710", "shopinfo": "0", "alias": [], "event": [], "indoor_map": "0", "email": [], "timestamp": "2026-05-29 20:23:41", "website": [], "address": "北京城区霄云路15号美食街后街", "space_num": [], "match": "0", "indoor_data": {"cmsid": [], "truefloor": [], "cpid": [], "floor": []}, "exit_location": [], "location": "116.466325,39.961275", "groupbuy_num": "0", "featured_reviews": []}, {"parent": [], "pcode": "110000", "keytag": "创意菜", "type": "餐饮服务;中餐厅;中餐厅", "photos": [{"title": [], "url": "http://store.is.autonavi.com/showpic/c6ea49c5643f17c857209e6651ad066d"}, {"title": "菜品", "url": "http://store.is.autonavi.com/showpic/83b74e330fa90e844b920f6f44b1f8f5"}, {"title": [], "url": "https://store.is.autonavi.com/showpic/7f7cceb598894be80000002095714134?type=pic"}], "building": [], "typecode": "050100", "poiweight": [], "citycode": "010", "adname": "东城区", "children": [], "featured_reviews_remake": [], "tel": "18513060136", "id": "B0FFIPM93S", "tag": "下午茶,牛肉,海参春卷", "entr_location": "116.424359,39.934402", "adcode": "110101", "pname": "北京市", "biz_type": "diner", "cityname": "北京市", "postcode": [], "business_area": "东四", "childtype": [], "atag": "下午茶,牛肉,海参春卷", "name": "曲廊院(东四十一条店)", "shopid": [], "favorite_num": [], "navi_poiid": [], "distance": [], "importance": [], "biz_ext": {"cost": "964.00", "opentime2": "周一至周日 11:30-14:00,18:00-21:00", "rating": "4.6", "open_time": "11:30-14:00 18:00-21:00", "meal_ordering": "0"}, "recommend": "0", "discount_num": "0", "gridcode": "5916732302", "shopinfo": "0", "alias": "水墨轩", "event": [], "indoor_map": "0", "email": [], "timestamp": "2026-05-27 00:08:56", "website": [], "address": "东四十一条25号", "space_num": [], "match": "0", "indoor_data": {"cmsid": [], "truefloor": [], "cpid": [], "floor": []}, "exit_location": [], "location": "116.424337,39.934460", "groupbuy_num": "0", "featured_reviews": []}, {"parent": [], "pcode": "110000", "keytag": "中餐", "type": "餐饮服务;中餐厅;中餐厅", "photos": [{"title": [], "url": "https://aos-comment.amap.com/B0I0FMLWIL/comment/content_media_external_images_media_100012753_1727173575561_24212984.jpg"}, {"title": [], "url": "https://aos-comment.amap.com/B0I0FMLWIL/comment/8C0CAB5E_5838_44C1_AEEA_A71C3054C85D_L0_001_1080_144_1753970956969_99012145.jpg"}, {"title": [], "url": "https://aos-comment.amap.com/B0I0FMLWIL/comment/content_media_external_file_2262_1747271228645_24903452.jpg"}], "building": [], "typecode": "050100", "poiweight": [], "citycode": "010", "adname": "丰台区", "children": [], "featured_reviews_remake": [], "tel": "010-63558820;18272551031", "id": "B0I0FMLWIL", "tag": "长安葫芦鸡,东市炙烤脆皮乳鸽,单人餐,双人餐", "entr_location": "116.36457,39.866647", "adcode": "110106", "pname": "北京市", "biz_type": "diner", "cityname": "北京市", "postcode": [], "business_area": "右安门", "childtype": [], "atag": "长安葫芦鸡,东市炙烤脆皮乳鸽,单人餐,双人餐", "name": "金狮麟·新豫菜(北京南站右安门店)", "shopid": [], "favorite_num": [], "navi_poiid": [], "distance": [], "importance": [], "biz_ext": {"cost": "268.00", "opentime2": "周一至周日 10:30-14:00,17:00-21:00", "rating": "4.6", "open_time": "10:30-14:00 17:00-21:00", "meal_ordering": "0"}, "recommend": "0", "discount_num": "0", "gridcode": "5916623920", "shopinfo": "0", "alias": "唐宴", "event": [], "indoor_map": "0", "email": [], "timestamp": "2026-05-30 15:29:54", "website": [], "address": "北京城区右安门外大街8号1层", "space_num": [], "match": "0", "indoor_data": {"cmsid": [], "truefloor": [], "cpid": [], "floor": []}, "exit_location": [], "location": "116.364799,39.866376", "groupbuy_num": "0", "featured_reviews": []}], "status": "1", "info": "OK"}}